git_fzf/__init__.py
git_fzf/commands/__init__.py
git_fzf/commands/add.py
git_fzf/commands/commit.py
git_fzf/commands/diff.py
git_fzf/commands/difftool.py
git_fzf/commands/reset.py
git_fzf/commands/restore.py
git_fzf/commands/switch.py
git_fzf/lib/__init__.py
git_fzf/lib/templates/InteractiveAddCommand.py
git_fzf/lib/templates/InteractiveCommand.py
git_fzf/lib/templates/InteractiveCommitCommand.py
git_fzf/lib/templates/InteractiveDiffCommand.py
git_fzf/lib/templates/InteractiveDiffLikeCommand.py
git_fzf/lib/templates/InteractiveDifftoolCommand.py
git_fzf/lib/templates/InteractiveResetCommand.py
git_fzf/lib/templates/InteractiveRestoreCommand.py
git_fzf/lib/templates/InteractiveSwitchCommand.py
git_fzf/lib/templates/__init__.py
git_fzf/lib/utils/__init__.py
git_fzf/lib/utils/errors.py
git_fzf/lib/utils/fzf.py
git_fzf/lib/utils/git.py
git_fzf/lib/utils/runtime.py
git_fzf/lib/utils/shell.py
git_fzf-0.0.2.dist-info/entry_points.txt
git_fzf-0.0.2.dist-info/LICENSE
git_fzf-0.0.2.dist-info/WHEEL
git_fzf-0.0.2.dist-info/METADATA
git_fzf-0.0.2.dist-info/RECORD
