Metadata-Version: 2.1
Name: git-fzf
Version: 0.0.2
Summary: Interactive versions of built-in Git commands using fzf
Home-page: https://github.com/openjck/git-fzf
License: MIT
Keywords: git,fzf,cli
Author: John Karahalis
Author-email: john.karahalis@gmail.com
Requires-Python: >=3.10,<4.0
Classifier: License :: OSI Approved :: MIT License
Classifier: Programming Language :: Python :: 3
Classifier: Programming Language :: Python :: 3.10
Requires-Dist: pyfzf (==0.2.2)
Project-URL: Documentation, https://github.com/openjck/git-fzf#usage
Project-URL: Repository, https://github.com/openjck/git-fzf
